gym_push/__init__.py
gym_push/envs/__init__.py
gym_push/envs/basic_env.py
gym_push/envs/evalumap1_env.py
gym_push/envs/evalumap2_env.py
gym_push/envs/data/notifications.csv
gym_push/envs/data/user_1/3months_Adaboost.joblib
gym_push/envs/data/user_1/3months_Decision Tree.joblib
gym_push/envs/data/user_1/3months_Naive Bayes.joblib
gym_push/envs/data/user_1/3months_Nearest Neighbors.joblib
gym_push/envs/data/user_1/3months_Random Forest.joblib
gym_push/envs/data/user_1/6months_Adaboost.joblib
gym_push/envs/data/user_1/6months_Decision Tree.joblib
gym_push/envs/data/user_1/6months_Naive Bayes.joblib
gym_push/envs/data/user_1/6months_Nearest Neighbors.joblib
gym_push/envs/data/user_1/6months_Random Forest.joblib
gym_push/envs/data/user_1/9months_Adaboost.joblib
gym_push/envs/data/user_1/9months_Decision Tree.joblib
gym_push/envs/data/user_1/9months_Naive Bayes.joblib
gym_push/envs/data/user_1/9months_Nearest Neighbors.joblib
gym_push/envs/data/user_1/9months_Random Forest.joblib
gym_push/envs/data/user_1/battery_3months.joblib
gym_push/envs/data/user_1/battery_6months.joblib
gym_push/envs/data/user_1/battery_9months.joblib
gym_push/envs/data/user_1/context_ohe.joblib
gym_push/envs/data/user_1/context_scaler.joblib
gym_push/envs/data/user_1/notif_ohe.joblib
gym_push/envs/data/user_1/test_set.csv
gym_push/envs/data/user_1/train_set.csv
gym_push/envs/data/user_1/validation_set.csv
gym_push/envs/data/user_5/3months_Adaboost.joblib
gym_push/envs/data/user_5/3months_Decision Tree.joblib
gym_push/envs/data/user_5/3months_Naive Bayes.joblib
gym_push/envs/data/user_5/3months_Nearest Neighbors.joblib
gym_push/envs/data/user_5/3months_Random Forest.joblib
gym_push/envs/data/user_5/6months_Adaboost.joblib
gym_push/envs/data/user_5/6months_Decision Tree.joblib
gym_push/envs/data/user_5/6months_Naive Bayes.joblib
gym_push/envs/data/user_5/6months_Nearest Neighbors.joblib
gym_push/envs/data/user_5/6months_Random Forest.joblib
gym_push/envs/data/user_5/9months_Adaboost.joblib
gym_push-0.0.21.dist-info/METADATA
gym_push-0.0.21.dist-info/WHEEL
gym_push-0.0.21.dist-info/top_level.txt
gym_push-0.0.21.dist-info/RECORD
