Metadata-Version: 2.1
Name: gym-push
Version: 0.0.21
Summary: UNKNOWN
Home-page: UNKNOWN
Author: Kieran Fraser
Author-email: kfraser@tcd.ie
License: UNKNOWN
Download-URL: https://github.com/kieranfraser/gym-push/raw/master/dist/gym-push-0.0.21.tar.gz
Platform: UNKNOWN
Requires-Dist: gym
Requires-Dist: numpy
Requires-Dist: pandas
Requires-Dist: joblib
Requires-Dist: eel
Requires-Dist: json-tricks
Requires-Dist: sklearn
Requires-Dist: seaborn
